confserver/__init__.py
confserver/__main__.py
confserver-0.0.6.dist-info/METADATA
confserver-0.0.6.dist-info/WHEEL
confserver-0.0.6.dist-info/top_level.txt
confserver-0.0.6.dist-info/RECORD
