Metadata-Version: 2.1
Name: confserver
Version: 0.0.6
Summary: Conf server
Home-page: UNKNOWN
Author: Vinogradov D
Author-email: dgrapes@gmail.com
License: MIT
Platform: UNKNOWN
Classifier: Programming Language :: Python :: 3
Classifier: License :: OSI Approved :: MIT License
Classifier: Operating System :: OS Independent
